{
  "skills": {
    "overall": {
      "rank": 216349,
      "level": 2103,
      "xp": 201851810
    },
    "attack": {
      "rank": 506254,
      "level": 95,
      "xp": 8908519
    },
    "defence": {
      "rank": 423627,
      "level": 95,
      "xp": 9411287
    },
    "strength": {
      "rank": 410456,
      "level": 99,
      "xp": 13743933
    },
    "hitpoints": {
      "rank": 262691,
      "level": 99,
      "xp": 24663423
    },
    "ranged": {
      "rank": 181289,
      "level": 99,
      "xp": 26894510
    },
    "prayer": {
      "rank": 303973,
      "level": 88,
      "xp": 4413855
    },
    "magic": {
      "rank": 223144,
      "level": 99,
      "xp": 16102197
    },
    "cooking": {
      "rank": 514222,
      "level": 92,
      "xp": 6903038
    },
    "woodcutting": {
      "rank": 363588,
      "level": 89,
      "xp": 5290482
    },
    "fletching": {
      "rank": 388980,
      "level": 91,
      "xp": 5967850
    },
    "fishing": {
      "rank": 451410,
      "level": 85,
      "xp": 3483351
    },
    "firemaking": {
      "rank": 387837,
      "level": 96,
      "xp": 9732804
    },
    "crafting": {
      "rank": 259342,
      "level": 93,
      "xp": 7605109
    },
    "smithing": {
      "rank": 274949,
      "level": 87,
      "xp": 4119679
    },
    "mining": {
      "rank": 182975,
      "level": 95,
      "xp": 9321400
    },
    "herblore": {
      "rank": 177889,
      "level": 93,
      "xp": 7324425
    },
    "agility": {
      "rank": 419510,
      "level": 80,
      "xp": 2066488
    },
    "thieving": {
      "rank": 389645,
      "level": 84,
      "xp": 3025034
    },
    "slayer": {
      "rank": 222516,
      "level": 97,
      "xp": 11527026
    },
    "farming": {
      "rank": 211638,
      "level": 99,
      "xp": 13434260
    },
    "runecrafting": {
      "rank": 299535,
      "level": 81,
      "xp": 2206301
    },
    "hunter": {
      "rank": 342325,
      "level": 84,
      "xp": 2981269
    },
    "construction": {
      "rank": 472929,
      "level": 83,
      "xp": 2725570
    }
  },
  "minigames": {
    "leaguePoints": {
      "rank": -1,
      "score": -1
    },
    "deadmanPoints": {
      "rank": -1,
      "score": -1
    },
    "bountyHunter": {
      "rank": -1,
      "score": -1
    },
    "bountyHunterRogues": {
      "rank": -1,
      "score": -1
    },
    "bountyHunterLegacy": {
      "rank": -1,
      "score": -1
    },
    "bountyHunterRoguesLegacy": {
      "rank": -1,
      "score": -1
    },
    "clueScrollsAll": {
      "rank": 201705,
      "score": 316
    },
    "clueScrollsBeginner": {
      "rank": 1669621,
      "score": 1
    },
    "clueScrollsEasy": {
      "rank": 212882,
      "score": 33
    },
    "clueScrollsMedium": {
      "rank": 157197,
      "score": 105
    },
    "clueScrollsHard": {
      "rank": 205780,
      "score": 123
    },
    "clueScrollsElite": {
      "rank": 102956,
      "score": 46
    },
    "clueScrollsMaster": {
      "rank": 196014,
      "score": 8
    },
    "lms": {
      "rank": 259448,
      "score": 550
    },
    "pvpArena": {
      "rank": -1,
      "score": -1
    },
    "soulWarsZeal": {
      "rank": 49643,
      "score": 2068
    },
    "riftsClosed": {
      "rank": 242181,
      "score": 152
    },
    "colosseumGlory": {
      "rank": 48365,
      "score": 31823
    },
    "collectionsLogged": {
      "rank": -1,
      "score": -1
    }
  },
  "bosses": {
    "abyssalSire": {
      "rank": 164205,
      "kills": 112
    },
    "alchemicalHydra": {
      "rank": 74690,
      "kills": 980
    },
    "amoxliatl": {
      "rank": 59965,
      "kills": 38
    },
    "araxxor": {
      "rank": 90986,
      "kills": 217
    },
    "artio": {
      "rank": -1,
      "kills": -1
    },
    "barrowsChests": {
      "rank": 430044,
      "kills": 123
    },
    "bryophyta": {
      "rank": 303589,
      "kills": 5
    },
    "callisto": {
      "rank": 85536,
      "kills": 167
    },
    "calvarion": {
      "rank": 75957,
      "kills": 145
    },
    "cerberus": {
      "rank": 146962,
      "kills": 459
    },
    "chambersOfXeric": {
      "rank": 169296,
      "kills": 73
    },
    "chambersOfXericChallengeMode": {
      "rank": 61473,
      "kills": 15
    },
    "chaosElemental": {
      "rank": -1,
      "kills": -1
    },
    "chaosFanatic": {
      "rank": 303639,
      "kills": 10
    },
    "commanderZilyana": {
      "rank": 200498,
      "kills": 47
    },
    "corporealBeast": {
      "rank": -1,
      "kills": -1
    },
    "crazyArchaeologist": {
      "rank": 392697,
      "kills": 16
    },
    "dagannothPrime": {
      "rank": 152410,
      "kills": 188
    },
    "dagannothRex": {
      "rank": 173028,
      "kills": 263
    },
    "dagannothSupreme": {
      "rank": 202331,
      "kills": 118
    },
    "derangedArchaeologist": {
      "rank": 120821,
      "kills": 25
    },
    "dukeSucellus": {
      "rank": 45797,
      "kills": 321
    },
    "generalGraardor": {
      "rank": 149948,
      "kills": 276
    },
    "giantMole": {
      "rank": 256543,
      "kills": 79
    },
    "grotesqueGuardians": {
      "rank": 299833,
      "kills": 22
    },
    "hespori": {
      "rank": 194265,
      "kills": 57
    },
    "kalphiteQueen": {
      "rank": 256917,
      "kills": 17
    },
    "kingBlackDragon": {
      "rank": 356545,
      "kills": 74
    },
    "kraken": {
      "rank": 461238,
      "kills": 192
    },
    "krilTsutsaroth": {
      "rank": -1,
      "kills": -1
    },
    "lunarChests": {
      "rank": 124423,
      "kills": 62
    },
    "mimic": {
      "rank": -1,
      "kills": -1
    },
    "nex": {
      "rank": 77656,
      "kills": 211
    },
    "nightmare": {
      "rank": 95318,
      "kills": 11
    },
    "phosanisNightmare": {
      "rank": -1,
      "kills": -1
    },
    "obor": {
      "rank": 343119,
      "kills": 5
    },
    "phantomMuspah": {
      "rank": 177240,
      "kills": 21
    },
    "sarachnis": {
      "rank": 172648,
      "kills": 54
    },
    "scorpia": {
      "rank": 209141,
      "kills": 11
    },
    "scurrius": {
      "rank": 262291,
      "kills": 25
    },
    "skotizo": {
      "rank": 112316,
      "kills": 40
    },
    "solHeredit": {
      "rank": 17328,
      "kills": 5
    },
    "spindel": {
      "rank": 80688,
      "kills": 63
    },
    "tempoross": {
      "rank": 483980,
      "kills": 40
    },
    "gauntlet": {
      "rank": 251347,
      "kills": 9
    },
    "corruptedGauntlet": {
      "rank": 39010,
      "kills": 560
    },
    "hueycoatl": {
      "rank": -1,
      "kills": -1
    },
    "leviathan": {
      "rank": -1,
      "kills": -1
    },
    "royalTitans": {
      "rank": 47824,
      "kills": 200
    },
    "whisperer": {
      "rank": -1,
      "kills": -1
    },
    "theatreOfBlood": {
      "rank": 82092,
      "kills": 16
    },
    "theatreOfBloodHardMode": {
      "rank": -1,
      "kills": -1
    },
    "thermonuclearSmokeDevil": {
      "rank": 201768,
      "kills": 184
    },
    "tombsOfAmascut": {
      "rank": 156376,
      "kills": 30
    },
    "tombsOfAmascutExpertMode": {
      "rank": 96766,
      "kills": 35
    },
    "tzKalZuk": {
      "rank": 13447,
      "kills": 5
    },
    "tzTokJad": {
      "rank": 170811,
      "kills": 7
    },
    "vardorvis": {
      "rank": 119666,
      "kills": 9
    },
    "venenatis": {
      "rank": 99369,
      "kills": 83
    },
    "vetion": {
      "rank": 30457,
      "kills": 263
    },
    "vorkath": {
      "rank": 458706,
      "kills": 73
    },
    "wintertodt": {
      "rank": 309125,
      "kills": 438
    },
    "yama": {
      "rank": -1,
      "kills": -1
    },
    "zalcano": {
      "rank": 21950,
      "kills": 507
    },
    "zulrah": {
      "rank": 151323,
      "kills": 779
    }
  }
}